{
    "name": "SanDisk",
    "offices": [
        {
            "address": "Building 10 Floor 2 Southwest Omer Industrial Park Omer Israel",
            "area": "Omer"
        },
        {
            "address": "Sderot HaTa'asiya & Sderot HaGalil Junction Migdal Tefen P.O. Box 3 Migdal Tefen 24959 Israel",
            "area": "Tefen"
        },
        {
            "address": "7 Atir Yeda St. Kfar Saba 44425, Israel",
            "area": "Kfar Saba"
        }
    ],
    "url": "https://www.sandisk.com/"
}